simple_name_parser.py
simple_name_parser-0.0.1.dist-info/METADATA
simple_name_parser-0.0.1.dist-info/WHEEL
simple_name_parser-0.0.1.dist-info/top_level.txt
simple_name_parser-0.0.1.dist-info/RECORD
