Metadata-Version: 2.2
Name: simple-name-parser
Version: 0.0.1
Summary: A simple class that parses names into their constituent parts
Author-email: "Mark D. Lattimore" <mark.d.lattimore@gmail.com>
Project-URL: Repository, https://github.com/mdlattimore/simple_name_parser
Requires-Python: >=3.8
